fibonacci_even_sum/__init__.py
fibonacci_even_sum/fibonacci_even_sum.py
fibonacci_even_sum/test_fibonacci_even_sum.py
fibonacci_even_sum-1.0.6.dist-info/LICENSE
fibonacci_even_sum-1.0.6.dist-info/METADATA
fibonacci_even_sum-1.0.6.dist-info/WHEEL
fibonacci_even_sum-1.0.6.dist-info/entry_points.txt
fibonacci_even_sum-1.0.6.dist-info/top_level.txt
fibonacci_even_sum-1.0.6.dist-info/RECORD
