Metadata-Version: 2.2
Name: fibonacci-even-sum
Version: 1.0.6
Summary: Fibonacci serisinin çift sayılarının toplamını hesaplayan bir Python CLI uygulaması
Home-page: https://github.com/huseyinaslim/fibonacci-even-sum
Author: Hüseyin ASLIM
Author-email: founder@codev.com.tr
License: MIT
Classifier: Programming Language :: Python :: 3
Classifier: Programming Language :: Python :: 3.6
Classifier: Programming Language :: Python :: 3.7
Classifier: Programming Language :: Python :: 3.8
Classifier: Programming Language :: Python :: 3.9
Classifier: Programming Language :: Python :: 3.10
Classifier: Programming Language :: Python :: 3.11
Classifier: License :: OSI Approved :: MIT License
Classifier: Operating System :: OS Independent
Requires-Python: >=3.6
License-File: LICENSE
Dynamic: author
Dynamic: author-email
Dynamic: classifier
Dynamic: description
Dynamic: description-content-type
Dynamic: home-page
Dynamic: license
Dynamic: requires-python
Dynamic: summary
